pollution_extraction/__init__.py
pollution_extraction/analyzer.py
pollution_extraction/cli.py
pollution_extraction/config.py
pollution_extraction/examples.py
pollution_extraction/utils.py
pollution_extraction/core/__init__.py
pollution_extraction/core/data_exporter.py
pollution_extraction/core/data_reader.py
pollution_extraction/core/data_visualizer.py
pollution_extraction/core/logging_utils.py
pollution_extraction/core/spatial_extractor.py
pollution_extraction/core/temporal_aggregator.py
pollution_extraction/core/exporters/__init__.py
pollution_extraction/core/exporters/_base.py
pollution_extraction/core/exporters/_main.py
pollution_extraction/core/exporters/_raster.py
pollution_extraction/core/exporters/_spatial.py
pollution_extraction/core/exporters/_tabular.py
pollution_extraction/core/exporters/base.py
pollution_extraction/core/exporters/main.py
pollution_extraction/core/exporters/raster.py
pollution_extraction/core/exporters/spatial.py
pollution_extraction/core/exporters/tabular.py
pollution_extraction/core/exporters/types.py
dss_pollution_extraction-1.0.3.dist-info/METADATA
dss_pollution_extraction-1.0.3.dist-info/WHEEL
dss_pollution_extraction-1.0.3.dist-info/entry_points.txt
dss_pollution_extraction-1.0.3.dist-info/licenses/LICENSE
dss_pollution_extraction-1.0.3.dist-info/RECORD
