Metadata-Version: 2.4
Name: dss-pollution-extraction
Version: 1.0.3
Summary: A package for analyzing pollution data from NetCDF files
Project-URL: homepage, https://github.com/MuhammadShafeeque/dss-pollution-extraction
Project-URL: documentation, https://dss-pollution-extraction.readthedocs.io/
Project-URL: repository, https://github.com/MuhammadShafeeque/dss-pollution-extraction
Project-URL: bug-tracker, https://github.com/MuhammadShafeeque/dss-pollution-extraction/issues
Project-URL: download, https://pypi.org/project/dss-pollution-extraction/
Author-email: Muhammad Shafeeque <muhammad.shafeeque@awi.de>
Maintainer-email: Muhammad Shafeeque <shafeequ@uni-bremen.de>
License: MIT License
License-File: LICENSE
Classifier: Intended Audience :: Education
Classifier: Intended Audience :: Science/Research
Classifier: License :: OSI Approved :: MIT License
Classifier: Operating System :: OS Independent
Classifier: Programming Language :: Python :: 3
Classifier: Topic :: Scientific/Engineering :: Atmospheric Science
Classifier: Topic :: Scientific/Engineering :: GIS
Requires-Python: >=3.11
Requires-Dist: build>=1.2.2.post1
Requires-Dist: bumpver>=2024.1130
Requires-Dist: cartopy>=0.20.0
Requires-Dist: dask>=2022.1.0
Requires-Dist: geopandas>=0.10.0
Requires-Dist: h5netcdf>=1.6.1
Requires-Dist: jupyter>=1.1.1
Requires-Dist: matplotlib>=3.5.0
Requires-Dist: nbsphinx>=0.9.7
Requires-Dist: netcdf4>=1.5.0
Requires-Dist: numpy>=1.21.0
Requires-Dist: pandas>=1.4.0
Requires-Dist: pyproj>=3.3.0
Requires-Dist: rasterio>=1.2.0
Requires-Dist: rioxarray>=0.11.0
Requires-Dist: scikit-learn>=1.0.0
Requires-Dist: scipy>=1.8.0
Requires-Dist: seaborn>=0.11.0
Requires-Dist: setuptools>=80.9.0
Requires-Dist: shapely>=1.8.0
Requires-Dist: sphinx>=8.1.3
Requires-Dist: twine>=6.1.0
Requires-Dist: xarray>=2022.3.0
Provides-Extra: dev
Requires-Dist: black; extra == 'dev'
Requires-Dist: flake8; extra == 'dev'
Requires-Dist: isort; extra == 'dev'
Requires-Dist: mypy; extra == 'dev'
Requires-Dist: pytest; extra == 'dev'
Requires-Dist: pytest-cov; extra == 'dev'
Provides-Extra: docs
Requires-Dist: ipython>=8.0.0; extra == 'docs'
Requires-Dist: myst-parser>=2.0.0; extra == 'docs'
Requires-Dist: nbsphinx>=0.9.0; extra == 'docs'
Requires-Dist: sphinx-autoapi>=2.0.0; extra == 'docs'
Requires-Dist: sphinx-copybutton>=0.5.0; extra == 'docs'
Requires-Dist: sphinx-design>=0.4.0; extra == 'docs'
Requires-Dist: sphinx-rtd-theme>=1.3.0; extra == 'docs'
Requires-Dist: sphinx>=6.0.0; extra == 'docs'
Provides-Extra: jupyter
Requires-Dist: folium; extra == 'jupyter'
Requires-Dist: ipywidgets; extra == 'jupyter'
Requires-Dist: jupyter; extra == 'jupyter'
Requires-Dist: plotly; extra == 'jupyter'
Provides-Extra: performance
Requires-Dist: bottleneck; extra == 'performance'
Requires-Dist: cython; extra == 'performance'
Requires-Dist: numba; extra == 'performance'
